dillinger/__init__.py
dillinger/bandits.py
dillinger/gaussian_process.py
dillinger/kernel_functions.py
dillinger/reward_generator.py
dillinger-1.0.0.dev1.dist-info/DESCRIPTION.rst
dillinger-1.0.0.dev1.dist-info/METADATA
dillinger-1.0.0.dev1.dist-info/RECORD
dillinger-1.0.0.dev1.dist-info/WHEEL
dillinger-1.0.0.dev1.dist-info/metadata.json
dillinger-1.0.0.dev1.dist-info/top_level.txt
