Metadata-Version: 2.0
Name: dillinger
Version: 1.0.0.dev1
Summary: Bayesian optimization for iterated multi-armed bandit     experiments.
Home-page: https://github.com/chipfranzen/dillinger
Author: Charles Franzen
Author-email: chip.franzen@gmail.com
License: MIT
Keywords: mutli-armed-bandits bayesian-optimization gaussian-processes
Platform: UNKNOWN
Classifier: Development Status :: 2 - Pre-Alpha
Classifier: Intended Audience :: Developers
Classifier: Intended Audience :: Science/Research
Classifier: Topic :: Scientific/Engineering :: Artificial Intelligence
Classifier: Topic :: Scientific/Engineering :: Information Analysis
Classifier: License :: OSI Approved :: MIT License
Classifier: Programming Language :: Python :: 3
Classifier: Programming Language :: Python :: 3.3
Classifier: Programming Language :: Python :: 3.4
Classifier: Programming Language :: Python :: 3.5
Classifier: Programming Language :: Python :: 3.6
Requires-Python: >=3
Requires-Dist: matplotlib
Requires-Dist: numpy
Requires-Dist: pandas
Requires-Dist: scipy
Requires-Dist: seaborn
